a3em/__init__.py
a3em/a3em.png
a3em/a3em_icon.png
a3em/dashboard.py
a3em/processing.py
a3em/read_config.py
a3em/relabel_logs.py
a3em/test.py
a3em/tkcal.py
a3em/write_config.py
a3em-1.0.3.dist-info/licenses/LICENSE
a3em-1.0.3.dist-info/METADATA
a3em-1.0.3.dist-info/WHEEL
a3em-1.0.3.dist-info/entry_points.txt
a3em-1.0.3.dist-info/top_level.txt
a3em-1.0.3.dist-info/RECORD
