Metadata-Version: 2.4
Name: a3em
Version: 1.0.3
Summary: A3EM Management Dashboard
Home-page: https://github.com/vu-a3em/a3em-dashboard
Author: Will Hedgecock
Author-email: ronald.w.hedgecock@vanderbilt.edu
Classifier: Programming Language :: Python :: 3
Classifier: Operating System :: OS Independent
Requires-Python: >=3.8
License-File: LICENSE
Requires-Dist: psutil
Requires-Dist: pytz
Requires-Dist: tzlocal
Requires-Dist: tk
Requires-Dist: babel
Requires-Dist: pandas
Requires-Dist: plotly
Dynamic: author
Dynamic: author-email
Dynamic: classifier
Dynamic: description
Dynamic: description-content-type
Dynamic: home-page
Dynamic: license-file
Dynamic: requires-dist
Dynamic: requires-python
Dynamic: summary
